integration_smoke/__init__.py
integration_smoke/smoke.py
integration_smoke_test-0.1.0.dist-info/licenses/LICENSE
integration_smoke_test-0.1.0.dist-info/METADATA
integration_smoke_test-0.1.0.dist-info/WHEEL
integration_smoke_test-0.1.0.dist-info/top_level.txt
integration_smoke_test-0.1.0.dist-info/RECORD
