Metadata-Version: 2.4
Name: integration-smoke-test
Version: 0.1.0
Summary: Lightweight Python library for fast API integration smoke tests with structured failure classification
Author: Rugved Chandekar
License: MIT
Project-URL: Homepage, https://github.com/rugvedchandekar/integration-smoke-test
Project-URL: Repository, https://github.com/rugvedchandekar/integration-smoke-test
Requires-Python: >=3.8
License-File: LICENSE
Requires-Dist: requests>=2.25
Dynamic: license-file
